shapeguard/__init__.py
shapeguard/dim_specs.py
shapeguard/exception.py
shapeguard/guard.py
shapeguard/parser.py
shapeguard/shape_spec.lark
shapeguard/shape_spec.py
shapeguard/shape_spec_parser.py
shapeguard/tools.py
shapeguard-0.1.1.dist-info/LICENSE
shapeguard-0.1.1.dist-info/WHEEL
shapeguard-0.1.1.dist-info/METADATA
shapeguard-0.1.1.dist-info/RECORD
