Metadata-Version: 2.1
Name: shapeguard
Version: 0.1.1
Summary: ShapeGuard is a tool to help with handling shapes in Tensorflow.
Home-page: https://github.com/Qwlouse/shapeguard
License: Apache-2.0
Author: Klaus Greff
Author-email: klaus.greff@startmail.com
Requires-Python: >=3.6,<4.0
Classifier: Development Status :: 4 - Beta
Classifier: Intended Audience :: Science/Research
Classifier: License :: OSI Approved :: Apache Software License
Classifier: Natural Language :: English
Classifier: Operating System :: OS Independent
Classifier: Programming Language :: Python :: 3
Classifier: Programming Language :: Python :: 3.5
Classifier: Programming Language :: Python :: 3.6
Classifier: Programming Language :: Python :: 3.7
Classifier: Topic :: Scientific/Engineering
Classifier: Topic :: Utilities
Requires-Dist: numpy (>=1.17,<2.0)
Requires-Dist: tensorflow (>=1.14,<2.0)
Requires-Dist: tensorflow-probability (>=0.7.0,<0.8.0)
Project-URL: Repository, https://github.com/Qwlouse/shapeguard
